colorprinttext/__init__.py
colorprinttext/colorprinttext.py
color_printtext-1.0.2.dist-info/LICENSE
color_printtext-1.0.2.dist-info/METADATA
color_printtext-1.0.2.dist-info/WHEEL
color_printtext-1.0.2.dist-info/top_level.txt
color_printtext-1.0.2.dist-info/RECORD
