Metadata-Version: 2.1
Name: color-printtext
Version: 1.0.2
Summary: PrintColor
Home-page: https://github.com/gx1285/Print-Color
Author: gx1285
Classifier: Programming Language :: Python :: 3.8
Classifier: Programming Language :: Python :: 3.9
Classifier: License :: OSI Approved :: MIT License
License-File: LICENSE
